chemcomp/__init__.py
chemcomp/accretion_models/__init__.py
chemcomp/accretion_models/_accretion_class.py
chemcomp/accretion_models/gas.py
chemcomp/accretion_models/pebbles.py
chemcomp/disks/__init__.py
chemcomp/disks/_chemistry.py
chemcomp/disks/_disk_class.py
chemcomp/disks/kees.py
chemcomp/disks/mmsn.py
chemcomp/disks/twopop.py
chemcomp/disks/_0pacity/__init__.py
chemcomp/disks/_0pacity/opacity_models.py
chemcomp/helpers/__init__.py
chemcomp/helpers/analysis_helper.py
chemcomp/helpers/import_config.py
chemcomp/helpers/main_helpers.py
chemcomp/helpers/solvediffonedee.py
chemcomp/helpers/tridag.py
chemcomp/helpers/units/__init__.py
chemcomp/helpers/units/berts_units.py
chemcomp/helpers/units/chemistry_const.py
chemcomp/planets/__init__.py
chemcomp/planets/_planet_class.py
chemcomp/planets/bertmigration.py
chemcomp/planets/migration_1.py
chemcomp/planets/no_accretion.py
chemcomp/planets/simple_planet.py
chemcomp-1.0.data/scripts/chemcomp_main
chemcomp-1.0.data/scripts/chemcomp_pipeline
chemcomp-1.0.dist-info/LICENSE.md
chemcomp-1.0.dist-info/METADATA
chemcomp-1.0.dist-info/WHEEL
chemcomp-1.0.dist-info/top_level.txt
chemcomp-1.0.dist-info/RECORD
