Metadata-Version: 2.1
Name: chemcomp
Version: 1.0
Summary: planet formation model including pebbles and gas accretion
Home-page: https://github.com/aarondavidschneider/chemcomp
Author: Aaron David Schneider
Author-email: aaron.schneider@nbi.ku.dk
License: MIT
Platform: UNKNOWN
Requires-Dist: astropy (>=4.0)
Requires-Dist: scipy
Requires-Dist: numpy
Requires-Dist: h5py
Requires-Dist: tables
Requires-Dist: python-slugify
Requires-Dist: matplotlib
Requires-Dist: pyyaml
Requires-Dist: parse
Requires-Dist: adjustText
